Metadata-Version: 2.1
Name: spidercloud-py
Version: 0.0.1
Summary: Python SDK for Spider Cloud API
Home-page: https://github.com/spider-rs/spider-clients/tree/main/python
Author: Spider
Author-email: jeff@a11ywatch.com
Classifier: Development Status :: 5 - Production/Stable
Classifier: Intended Audience :: Developers
Classifier: Intended Audience :: Information Technology
Classifier: Topic :: Software Development :: Libraries :: Python Modules
Classifier: Topic :: Internet
Classifier: Topic :: Internet :: WWW/HTTP
Classifier: Topic :: Internet :: WWW/HTTP :: Indexing/Search
Classifier: License :: OSI Approved :: MIT License
Classifier: Operating System :: OS Independent
License-File: LICENSE
